setup.py
piengine/__init__.py
piengine/__main__.py
piengine.egg-info/PKG-INFO
piengine.egg-info/SOURCES.txt
piengine.egg-info/dependency_links.txt
piengine.egg-info/entry_points.txt
piengine.egg-info/requires.txt
piengine.egg-info/top_level.txt
piengine/src/__init__.py
piengine/src/mainloop.py
piengine/src/printloop.py
piengine/src/base/__init__.py
piengine/src/base/drawable.py
piengine/src/base/updateable.py
piengine/src/events/__init__.py
piengine/src/events/event.py
piengine/src/events/event_handler.py
piengine/src/events/keyboard_event.py
piengine/src/events/mouse_event.py
piengine/src/game/__init__.py
piengine/src/game/game.py
piengine/src/game/scene.py
piengine/src/objects/__init__.py
piengine/src/objects/game_object.py
piengine/src/objects/object.py
piengine/src/objects/text.py
piengine/src/print/__init__.py
piengine/src/print/print.py