Metadata-Version: 2.1
Name: piengine
Version: 0.0.1
Summary: Pi Game Engine
Author: Etkin Dogan
Author-email: etkindogan@gmail.com
Requires-Python: >=3.8
